cli.py
entries-0.1.2.dist-info/LICENSE
entries-0.1.2.dist-info/METADATA
entries-0.1.2.dist-info/WHEEL
entries-0.1.2.dist-info/entry_points.txt
entries-0.1.2.dist-info/top_level.txt
entries-0.1.2.dist-info/RECORD
