Metadata-Version: 2.1
Name: entries
Version: 0.1.2
Summary: Micropub client for the terminal
Home-page: https://github.com/tsileo/entries
Author: Thomas Sileo
Author-email: t@a4.io
License: OSI Approved :: ISC License (ISCL)
Platform: UNKNOWN
Requires-Python: >=3.6
Requires-Dist: pyyaml
Requires-Dist: mf2py
Requires-Dist: click
Requires-Dist: requests
